{
	"credit": "Made with Blockbench",
	"textures": {
		"0": "block/Custom_Texture/Sans_titre-1",
		"1": "block/deepslate_tiles_stairs_bottom",
		"particle": "block/Custom_Texture/Sans_titre-1"
	},
	"elements": [
		{
			"from": [6, -16, -1],
			"to": [11, -15, 0],
			"rotation": {"angle": 0, "axis": "y", "origin": [8.45, -9.25, -8.00898]},
			"faces": {
				"north": {"uv": [0, 0, 5, 1], "texture": "#1"},
				"east": {"uv": [0, 0, 1, 1], "texture": "#1"},
				"south": {"uv": [0, 0, 5, 1], "texture": "#1"},
				"west": {"uv": [0, 0, 1, 1], "texture": "#1"},
				"up": {"uv": [0, 0, 5, 1], "texture": "#1"},
				"down": {"uv": [0, 0, 5, 1], "texture": "#1"}
			}
		},
		{
			"from": [8.11719, -12.19922, -0.96106],
			"to": [9.11719, -11.19922, 14.61631],
			"rotation": {"angle": 0, "axis": "y", "origin": [8.5, -11.69922, -0.5]},
			"faces": {
				"north": {"uv": [0, 0, 1, 1], "texture": "#1"},
				"east": {"uv": [0, 0, 15.57737, 1], "texture": "#1"},
				"south": {"uv": [0, 0, 1, 1], "texture": "#1"},
				"west": {"uv": [0, 0, 15.57737, 1], "texture": "#1"},
				"up": {"uv": [0, 0, 1, 15.57737], "texture": "#1"},
				"down": {"uv": [0, 0, 1, 15.57737], "texture": "#1"}
			}
		},
		{
			"from": [4.875, -12.19922, 15.06237],
			"to": [5.875, -11.19922, 31.09677],
			"rotation": {"angle": -22.5, "axis": "y", "origin": [8.61719, -11.69922, 22.98387]},
			"faces": {
				"north": {"uv": [0, 0, 1, 1], "texture": "#1"},
				"east": {"uv": [0, 0, 16, 1], "texture": "#1"},
				"south": {"uv": [0, 0, 1, 1], "texture": "#1"},
				"west": {"uv": [0, 0, 16, 1], "texture": "#1"},
				"up": {"uv": [0, 0, 1, 16], "texture": "#1"},
				"down": {"uv": [0, 0, 1, 16], "texture": "#1"}
			}
		},
		{
			"from": [11.89338, -12.19922, -14.9375],
			"to": [12.89338, -11.19922, -0.88747],
			"rotation": {"angle": -22.5, "axis": "y", "origin": [10.1551, -11.69922, -10.42336]},
			"faces": {
				"north": {"uv": [0, 0, 1, 1], "texture": "#1"},
				"east": {"uv": [0, 0, 14.05003, 1], "texture": "#1"},
				"south": {"uv": [0, 0, 1, 1], "texture": "#1"},
				"west": {"uv": [0, 0, 14.05003, 1], "texture": "#1"},
				"up": {"uv": [0, 0, 1, 14.05003], "texture": "#1"},
				"down": {"uv": [0, 0, 1, 14.05003], "texture": "#1"}
			}
		},
		{
			"from": [4.875, 18.80078, 15.06237],
			"to": [5.875, 19.80078, 31.09677],
			"rotation": {"angle": -22.5, "axis": "y", "origin": [8.61719, 19.30078, 22.98387]},
			"faces": {
				"north": {"uv": [0, 0, 1, 1], "texture": "#1"},
				"east": {"uv": [0, 0, 16, 1], "texture": "#1"},
				"south": {"uv": [0, 0, 1, 1], "texture": "#1"},
				"west": {"uv": [0, 0, 16, 1], "texture": "#1"},
				"up": {"uv": [0, 0, 1, 16], "texture": "#1"},
				"down": {"uv": [0, 0, 1, 16], "texture": "#1"}
			}
		},
		{
			"from": [8.11719, 18.80078, -0.96106],
			"to": [9.11719, 19.80078, 14.61631],
			"rotation": {"angle": 0, "axis": "y", "origin": [8.5, 19.30078, -0.5]},
			"faces": {
				"north": {"uv": [0, 0, 1, 1], "texture": "#1"},
				"east": {"uv": [0, 0, 15.57737, 1], "texture": "#1"},
				"south": {"uv": [0, 0, 1, 1], "texture": "#1"},
				"west": {"uv": [0, 0, 15.57737, 1], "texture": "#1"},
				"up": {"uv": [0, 0, 1, 15.57737], "texture": "#1"},
				"down": {"uv": [0, 0, 1, 15.57737], "texture": "#1"}
			}
		},
		{
			"from": [11.89338, 18.80078, -14.9375],
			"to": [12.89338, 19.80078, -0.89138],
			"rotation": {"angle": -22.5, "axis": "y", "origin": [10.1551, 19.30078, -10.42336]},
			"faces": {
				"north": {"uv": [0, 0, 1, 1], "texture": "#1"},
				"east": {"uv": [0, 0, 14.04612, 1], "texture": "#1"},
				"south": {"uv": [0, 0, 1, 1], "texture": "#1"},
				"west": {"uv": [0, 0, 14.04612, 1], "texture": "#1"},
				"up": {"uv": [0, 0, 1, 14.04612], "texture": "#1"},
				"down": {"uv": [0, 0, 1, 14.04612], "texture": "#1"}
			}
		},
		{
			"from": [11.85156, -16, -16],
			"to": [16.85156, -15, -15],
			"rotation": {"angle": -22.5, "axis": "y", "origin": [8.45, -9.25, -15.50898]},
			"faces": {
				"north": {"uv": [0, 0, 5, 1], "texture": "#1"},
				"east": {"uv": [0, 0, 1, 1], "texture": "#1"},
				"south": {"uv": [0, 0, 5, 1], "texture": "#1"},
				"west": {"uv": [0, 0, 1, 1], "texture": "#1"},
				"up": {"uv": [0, 0, 5, 1], "texture": "#1"},
				"down": {"uv": [0, 0, 5, 1], "texture": "#1"}
			}
		},
		{
			"from": [13.85156, -15, -15.91797],
			"to": [14.65156, 19.5, -15.11797],
			"rotation": {"angle": -22.5, "axis": "y", "origin": [8.45, -9.25, -15.50898]},
			"faces": {
				"north": {"uv": [0, 0, 0.8, 16], "texture": "#1"},
				"east": {"uv": [0, 0, 0.8, 16], "texture": "#1"},
				"south": {"uv": [0, 0, 0.8, 16], "texture": "#1"},
				"west": {"uv": [0, 0, 0.8, 16], "texture": "#1"},
				"up": {"uv": [0, 0, 0.8, 0.8], "texture": "#1"},
				"down": {"uv": [0, 0, 0.8, 0.8], "texture": "#1"}
			}
		},
		{
			"from": [8.21439, -15, -0.87775],
			"to": [9.01439, 19.5, -0.07775],
			"rotation": {"angle": 0, "axis": "y", "origin": [7.66907, -3, -0.54416]},
			"faces": {
				"north": {"uv": [0, 0, 0.8, 16], "texture": "#1"},
				"east": {"uv": [0, 0, 0.8, 16], "texture": "#1"},
				"south": {"uv": [0, 0, 0.8, 16], "texture": "#1"},
				"west": {"uv": [0, 0, 0.8, 16], "texture": "#1"},
				"up": {"uv": [0, 0, 0.8, 0.8], "texture": "#1"},
				"down": {"uv": [0, 0, 0.8, 0.8], "texture": "#1"}
			}
		},
		{
			"from": [8.16751, -15, 14.11444],
			"to": [8.96751, 19.5, 14.91444],
			"rotation": {"angle": 0, "axis": "y", "origin": [8.61439, -3, 14.51444]},
			"faces": {
				"north": {"uv": [0, 0, 0.8, 16], "texture": "#1"},
				"east": {"uv": [0, 0, 0.8, 16], "texture": "#1"},
				"south": {"uv": [0, 0, 0.8, 16], "texture": "#1"},
				"west": {"uv": [0, 0, 0.8, 16], "texture": "#1"},
				"up": {"uv": [0, 0, 0.8, 0.8], "texture": "#1"},
				"down": {"uv": [0, 0, 0.8, 0.8], "texture": "#1"}
			}
		},
		{
			"from": [19.73438, -15, 27.19531],
			"to": [20.53438, 19.5, 27.99531],
			"rotation": {"angle": -22.5, "axis": "y", "origin": [8.45, -9.25, -15.50898]},
			"faces": {
				"north": {"uv": [0, 0, 0.8, 16], "texture": "#1"},
				"east": {"uv": [0, 0, 0.8, 16], "texture": "#1"},
				"south": {"uv": [0, 0, 0.8, 16], "texture": "#1"},
				"west": {"uv": [0, 0, 0.8, 16], "texture": "#1"},
				"up": {"uv": [0, 0, 0.8, 0.8], "texture": "#1"},
				"down": {"uv": [0, 0, 0.8, 0.8], "texture": "#1"}
			}
		},
		{
			"from": [5.91406, -16, 14],
			"to": [10.91406, -15, 15],
			"rotation": {"angle": 0, "axis": "y", "origin": [0, -16, 0]},
			"faces": {
				"north": {"uv": [0, 0, 5, 1], "texture": "#1"},
				"east": {"uv": [0, 0, 1, 1], "texture": "#1"},
				"south": {"uv": [0, 0, 5, 1], "texture": "#1"},
				"west": {"uv": [0, 0, 1, 1], "texture": "#1"},
				"up": {"uv": [0, 0, 5, 1], "texture": "#1"},
				"down": {"uv": [0, 0, 5, 1], "texture": "#1"}
			}
		},
		{
			"from": [-0.33594, -16, 30.69531],
			"to": [4.66406, -15, 31.69531],
			"rotation": {"angle": -22.5, "axis": "y", "origin": [8.5, -15.5, 31.5]},
			"faces": {
				"north": {"uv": [0, 0, 5, 1], "texture": "#1"},
				"east": {"uv": [0, 0, 1, 1], "texture": "#1"},
				"south": {"uv": [0, 0, 5, 1], "texture": "#1"},
				"west": {"uv": [0, 0, 1, 1], "texture": "#1"},
				"up": {"uv": [0, 0, 5, 1], "texture": "#1"},
				"down": {"uv": [0, 0, 5, 1], "texture": "#1"}
			}
		},
		{
			"from": [19.98438, -12, 12.17188],
			"to": [20.03438, 16.5, 27.49531],
			"rotation": {"angle": -22.5, "axis": "y", "origin": [8.45, -9.25, -15.50898]},
			"faces": {
				"north": {"uv": [7.46067, 0, 15.96854, 12.04494], "texture": "#0"},
				"east": {"uv": [4.67416, 0.53933, 13.18202, 15.64045], "texture": "#0"},
				"south": {"uv": [7.46067, 0, 15.96854, 12.04494], "texture": "#0"},
				"west": {"uv": [0, 0.62921, 8.50787, 15.73034], "texture": "#0"},
				"up": {"uv": [7.46067, 0, 15.96854, 12.04494], "texture": "#0"},
				"down": {"uv": [7.46067, 0, 15.96854, 12.04494], "texture": "#0"}
			}
		},
		{
			"from": [8.7702, -12, -0.37339],
			"to": [8.8202, 16.5, 14.42661],
			"rotation": {"angle": 0, "axis": "y", "origin": [11.62723, 4.25, 7.02661]},
			"faces": {
				"north": {"uv": [7.46067, 0, 15.96854, 12.04494], "texture": "#0"},
				"east": {"uv": [0.17978, 0, 8.68764, 15.10112], "texture": "#0"},
				"south": {"uv": [7.46067, 0, 15.96854, 12.04494], "texture": "#0"},
				"west": {"uv": [7.46067, 0.89888, 15.96854, 16], "texture": "#0"},
				"up": {"uv": [7.46067, 0, 15.96854, 12.04494], "texture": "#0"},
				"down": {"uv": [7.46067, 0, 15.96854, 12.04494], "texture": "#0"}
			}
		},
		{
			"from": [14.21875, -12, -15.30469],
			"to": [14.26875, 16.5, -1.23516],
			"rotation": {"angle": -22.5, "axis": "y", "origin": [8.45, -9.25, -15.50898]},
			"faces": {
				"north": {"uv": [7.46067, 0, 15.96854, 12.04494], "texture": "#0"},
				"east": {"uv": [7.49213, 0.89888, 16, 16], "texture": "#0"},
				"south": {"uv": [7.46067, 0, 15.96854, 12.04494], "texture": "#0"},
				"west": {"uv": [0, 0, 8.50787, 15.10112], "texture": "#0"},
				"up": {"uv": [7.46067, 0, 15.96854, 12.04494], "texture": "#0"},
				"down": {"uv": [7.46067, 0, 15.96854, 12.04494], "texture": "#0"}
			}
		}
	],
	"display": {
		"thirdperson_righthand": {
			"translation": [-0.5, 0.75, -3],
			"scale": [0.2, 0.2, 0.2]
		},
		"thirdperson_lefthand": {
			"translation": [-0.5, 0.75, -3],
			"scale": [0.2, 0.2, 0.2]
		},
		"firstperson_righthand": {
			"translation": [0, 3.75, 4.5],
			"scale": [0.5, 0.5, 0.5]
		},
		"firstperson_lefthand": {
			"translation": [0, 3.75, 4.5],
			"scale": [0.5, 0.5, 0.5]
		},
		"ground": {
			"translation": [0, 8.25, 0],
			"scale": [0.5, 0.5, 0.5]
		},
		"gui": {
			"rotation": [49, -36.75, 0],
			"translation": [0, 1.25, 0],
			"scale": [0.3, 0.3, 0.3]
		},
		"head": {
			"translation": [0, 8.75, 0],
			"scale": [2.2, 2.2, 2.2]
		}
	},
	"groups": [
		0,
		1,
		2,
		3,
		4,
		5,
		6,
		7,
		8,
		9,
		10,
		11,
		12,
		13,
		{
			"name": "group",
			"origin": [8.45, -9.25, -15.50898],
			"color": 0,
			"children": [14, 15, 16]
		}
	]
}